babel_vue_extractor-1.4.3.dist-info/METADATA
babel_vue_extractor-1.4.3.dist-info/RECORD
babel_vue_extractor-1.4.3.dist-info/WHEEL
babel_vue_extractor-1.4.3.dist-info/top_level.txt
babelvueextractor/__init__.py
babelvueextractor/extract.py
babelvueextractor/lexer.py
babelvueextractor/tests/__init__.py
babelvueextractor/tests/test_extractor.py
babelvueextractor/tests/test_lexer.py
