Metadata-Version: 2.1
Name: babel-vue-extractor
Version: 1.4.3
Summary: A plugin for babel to work with vue.js templates
Home-page: https://github.com/nonamenix/babel-vue-extractor
Author: Danil Ivanov
Author-email: nonamenix@gmail.com
License: Apache Software License
Keywords: vuejs babel
Platform: UNKNOWN
Classifier: Intended Audience :: Developers
Classifier: Topic :: Software Development :: Internationalization
Classifier: License :: OSI Approved :: Apache Software License
Classifier: Programming Language :: Python :: 2
Classifier: Programming Language :: Python :: 2.7
Classifier: Programming Language :: Python :: 3
Classifier: Programming Language :: Python :: 3.5
Classifier: Programming Language :: Python :: 3.6
Provides-Extra: test
Provides-Extra: dev
Requires-Dist: babel
Requires-Dist: six
Provides-Extra: dev
Requires-Dist: check-manifest; extra == 'dev'
Requires-Dist: nose; extra == 'dev'
Provides-Extra: test
Requires-Dist: coverage; extra == 'test'
